cbr_dws_client/__init__.py
cbr_dws_client/base.py
cbr_dws_client/constants.py
cbr_dws_client/mixins.py
cbr_dws_client-0.0.9.dist-info/LICENSE
cbr_dws_client-0.0.9.dist-info/METADATA
cbr_dws_client-0.0.9.dist-info/WHEEL
cbr_dws_client-0.0.9.dist-info/RECORD
