Metadata-Version: 2.3
Name: cbr-dws-client
Version: 0.0.9
Summary: Клиент для работы с сервисом получения ежедневных данных ЦБ РФ.
License: Apache-2.0
Author: Sergey V. Elfimov
Author-email: elfimovserg@gmail.com
Requires-Python: >=3.11,<4.0
Classifier: License :: OSI Approved :: Apache Software License
Classifier: Natural Language :: English
Classifier: Operating System :: OS Independent
Classifier: Programming Language :: Python
Classifier: Programming Language :: Python :: 3
Classifier: Programming Language :: Python :: 3.11
Classifier: Programming Language :: Python :: 3.12
Classifier: Programming Language :: Python :: 3.13
Classifier: Programming Language :: Python :: 3 :: Only
Requires-Dist: httpx (<0.28)
Requires-Dist: zeep (>=4.2.1)
Project-URL: Repository, https://github.com/SergeiVElfimov/cbr-dws-client
